loopers/__init__.py
loopers-1.4.dist-info/LICENCE.txt
loopers-1.4.dist-info/METADATA
loopers-1.4.dist-info/WHEEL
loopers-1.4.dist-info/top_level.txt
loopers-1.4.dist-info/RECORD
