Metadata-Version: 2.1
Name: loopers
Version: 1.4
Summary: An email scrapper
Home-page: https://github.com/sirrobot01/loopers
Author: Akere Mukhtar Abiodun
Author-email: akeremukhtar10@gmail.com
License: UNKNOWN
Platform: UNKNOWN
Requires-Dist: requests
Requires-Dist: bs4
